TODO
setup.py
vnstaty/__init__.py
vnstaty/_vnstaty.c
vnstaty/daemon.py
vnstaty/ifinfo.c
vnstaty/ifinfo.h
vnstaty/interface.py
vnstaty/model.py
vnstaty/settings.py
vnstaty.egg-info/PKG-INFO
vnstaty.egg-info/SOURCES.txt
vnstaty.egg-info/dependency_links.txt
vnstaty.egg-info/requires.txt
vnstaty.egg-info/top_level.txt