Metadata-Version: 1.0
Name: vnstaty
Version: 0.3
Summary: Python implementation of vnstat.
Home-page: UNKNOWN
Author: Sergio Campos
Author-email: seocam@seocam.net
License: PSF
Platform: UNKNOWN
